agentless/__init__.py
agentless-1.2.dist-info/LICENSE.md
agentless-1.2.dist-info/METADATA
agentless-1.2.dist-info/WHEEL
agentless-1.2.dist-info/top_level.txt
agentless-1.2.dist-info/zip-safe
agentless-1.2.dist-info/RECORD
