Metadata-Version: 2.1
Name: agentless
Version: 1.2
Summary: This tool can help you scan the network
Home-page: https://github.com/CastellaniDavide/agentless
Author: CastellaniDavide
Author-email: help@castellanidavide.it
License: GNU
Platform: linux_distibution
Requires-Python: >=3.6
Requires-Dist: tabular-log (>=2.7)
Requires-Dist: requests
